napari_amdtrk/__init__.py
napari_amdtrk/_reader.py
napari_amdtrk/_sample_data.py
napari_amdtrk/_utils.py
napari_amdtrk/_widget.py
napari_amdtrk/napari.yaml
napari_amdtrk/_tests/__init__.py
napari_amdtrk/_tests/test_reader.py
napari_amdtrk/_tests/test_sample_data.py
napari_amdtrk/_tests/test_widget.py
napari_amdtrk-1.1.0.dist-info/LICENSE
napari_amdtrk-1.1.0.dist-info/METADATA
napari_amdtrk-1.1.0.dist-info/WHEEL
napari_amdtrk-1.1.0.dist-info/entry_points.txt
napari_amdtrk-1.1.0.dist-info/top_level.txt
napari_amdtrk-1.1.0.dist-info/RECORD
