Metadata-Version: 2.1
Name: napari-amdtrk
Version: 1.1.0
Summary: Manually amend segmentation and track within napari
Home-page: https://github.com/Jeff-Gui/napari-amdtrk-plugin
Author: Yifan Gui
Author-email: jeffgui9912@gmail.com
License: MIT
Project-URL: Bug Tracker, https://github.com/Jeff-Gui/napari-amdtrk-plugin/issues
Project-URL: Documentation, https://github.com/Jeff-Gui/napari-amdtrk-plugin/blob/master/README.md
Project-URL: Source Code, https://github.com/Jeff-Gui/napari-amdtrk-plugin
Classifier: Development Status :: 3 - Alpha
Classifier: Framework :: napari
Classifier: Intended Audience :: Developers
Classifier: License :: OSI Approved :: MIT License
Classifier: Operating System :: OS Independent
Classifier: Programming Language :: Python
Classifier: Programming Language :: Python :: 3
Classifier: Programming Language :: Python :: 3 :: Only
Classifier: Programming Language :: Python :: 3.8
Classifier: Programming Language :: Python :: 3.9
Classifier: Programming Language :: Python :: 3.10
Classifier: Topic :: Scientific/Engineering :: Image Processing
Requires-Python: >=3.8
License-File: LICENSE
Requires-Dist: numpy (<1.24)
Requires-Dist: magicgui
Requires-Dist: qtpy
Requires-Dist: trackpy
Requires-Dist: pandas
Requires-Dist: scikit-image
Provides-Extra: testing
Requires-Dist: tox ; extra == 'testing'
Requires-Dist: pytest ; extra == 'testing'
Requires-Dist: pytest-cov ; extra == 'testing'
Requires-Dist: pytest-qt ; extra == 'testing'
Requires-Dist: napari ; extra == 'testing'
Requires-Dist: pyqt5 ; extra == 'testing'
